{
  "rooms": {
    "#room_dummy": {
      "description": "Dummy room.",
      "directions": {
      },
      "items": [
      ],
      "creatures": []
    }
  },
  "creatures": {
    "#dummy_creature": {
      "alias_BUG": [
        "dummy creature"
      ],
      "health": 10,
      "damage": 10,
      "drops": [
      ],
      "description": "Dummy creature"
    }
  },
  "items": {
    "regular": {
    },
    "consumable": {
    }
  },
  "equipment": {
    "weapons": {
    },
    "armour": {
    }
  },
  "environment_objects": {
  },
  "hero": {
    "health": 100,
    "location": "#room_dummy",
    "right_hand": "none",
    "left_hand": "none",
    "head": "none",
    "chest": "none",
    "legs": "none",
    "actions": {
    },
    "inventory": []
  }
}